Metadata-Version: 1.0
Name: chubby
Version: 0.2.3
Summary: Misc. GitHub actions in your terminal
Home-page: http://meetmangukiya.github.io
Author: Meet Mangukiya
Author-email: meetmangukiya98@gmail.com
License: MIT
Platform: UNKNOWN
